jdlinker/__init__.py
jdlinker/jdlinker.py
sphinx_JDLinker-2.0.1.dist-info/LICENSE.txt
sphinx_JDLinker-2.0.1.dist-info/METADATA
sphinx_JDLinker-2.0.1.dist-info/WHEEL
sphinx_JDLinker-2.0.1.dist-info/top_level.txt
sphinx_JDLinker-2.0.1.dist-info/RECORD
