Metadata-Version: 2.1
Name: sphinx-JDLinker
Version: 2.0.1
Summary: A sphinx extension designed to allow you to create links to a JavaDoc website from your sphinx documentation.
Home-page: https://github.com/NariKiro/sphinx-JDLinker
Author: NariKiro
Author-email: narikiro@pm.me
License: MIT
Keywords: javadoc link sphinx documentation
Platform: UNKNOWN
Classifier: Development Status :: 4 - Beta
Classifier: Framework :: Sphinx :: Extension
Classifier: Intended Audience :: Developers
Classifier: License :: OSI Approved :: MIT License
Classifier: Natural Language :: English
Classifier: Programming Language :: Java
Classifier: Programming Language :: Python
Classifier: Topic :: Documentation :: Sphinx
Requires-Dist: sphinx (>=2.0.0)
